RedditReader/__init__.py
RedditReader-1.0.dist-info/LICENSE.txt
RedditReader-1.0.dist-info/METADATA
RedditReader-1.0.dist-info/WHEEL
RedditReader-1.0.dist-info/top_level.txt
RedditReader-1.0.dist-info/RECORD
