Metadata-Version: 2.1
Name: RedditReader
Version: 1.0
Summary: RedditReader is a package to get random images from any Subreddit available on Reddit.
Home-page: https://www.google.com
Author: toxicrecker
Author-email: reck.channel.mainlead@gmail.com
License: UNKNOWN
Platform: UNKNOWN
Classifier: Programming Language :: Python :: 3
Classifier: License :: OSI Approved :: MIT License
Classifier: Operating System :: OS Independent
Requires-Python: >=3.6
